change_data_capture/__init__.py
change_data_capture/main.py
change_data_capture-0.0.1.dist-info/METADATA
change_data_capture-0.0.1.dist-info/WHEEL
change_data_capture-0.0.1.dist-info/top_level.txt
change_data_capture-0.0.1.dist-info/RECORD
