Metadata-Version: 2.1
Name: change_data_capture
Version: 0.0.1
Summary: Change data capture to compare two dataframe and output add, change and delete records
Author: Dhivya Nagasubramanian
Author-email: nagas021@alumni.umn.edu
Classifier: Programming Language :: Python :: 3
Classifier: License :: OSI Approved :: MIT License
Classifier: Operating System :: OS Independent
Requires-Python: >=3.6
